myutils_ethank5149/__init__.py
myutils_ethank5149/linspace.py
myutils_ethank5149/math.py
tests/__init__.py
tests/test_linspace.py
myutils_ethank5149-0.1.1.dist-info/LICENSE
myutils_ethank5149-0.1.1.dist-info/METADATA
myutils_ethank5149-0.1.1.dist-info/WHEEL
myutils_ethank5149-0.1.1.dist-info/top_level.txt
myutils_ethank5149-0.1.1.dist-info/RECORD
