Metadata-Version: 2.1
Name: myutils-ethank5149
Version: 0.1.1
Summary: Frequently used function and math utilities
Home-page: https://github.com/ethank5149/myutils_ethank5149
Author: Ethan Knox
Author-email: ethank5149@gmail.com.com
License: MIT
Platform: UNKNOWN
Classifier: Programming Language :: Python :: 3
Classifier: License :: OSI Approved :: MIT License
Classifier: Operating System :: OS Independent
Requires-Python: >=3.6
Requires-Dist: wheel
Requires-Dist: pytest
